sports_odds_api/__init__.py
sports_odds_api/_base_client.py
sports_odds_api/_client.py
sports_odds_api/_compat.py
sports_odds_api/_constants.py
sports_odds_api/_exceptions.py
sports_odds_api/_files.py
sports_odds_api/_models.py
sports_odds_api/_qs.py
sports_odds_api/_resource.py
sports_odds_api/_response.py
sports_odds_api/_streaming.py
sports_odds_api/_types.py
sports_odds_api/_version.py
sports_odds_api/_wrappers.py
sports_odds_api/pagination.py
sports_odds_api/py.typed
sports_odds_api/_utils/__init__.py
sports_odds_api/_utils/_compat.py
sports_odds_api/_utils/_datetime_parse.py
sports_odds_api/_utils/_logs.py
sports_odds_api/_utils/_proxy.py
sports_odds_api/_utils/_reflection.py
sports_odds_api/_utils/_resources_proxy.py
sports_odds_api/_utils/_streams.py
sports_odds_api/_utils/_sync.py
sports_odds_api/_utils/_transform.py
sports_odds_api/_utils/_typing.py
sports_odds_api/_utils/_utils.py
sports_odds_api/lib/.keep
sports_odds_api/resources/__init__.py
sports_odds_api/resources/account.py
sports_odds_api/resources/events.py
sports_odds_api/resources/leagues.py
sports_odds_api/resources/players.py
sports_odds_api/resources/sports.py
sports_odds_api/resources/stats.py
sports_odds_api/resources/stream.py
sports_odds_api/resources/teams.py
sports_odds_api/types/__init__.py
sports_odds_api/types/account_usage.py
sports_odds_api/types/event.py
sports_odds_api/types/event_get_params.py
sports_odds_api/types/league.py
sports_odds_api/types/league_get_params.py
sports_odds_api/types/league_get_response.py
sports_odds_api/types/player.py
sports_odds_api/types/player_get_params.py
sports_odds_api/types/rate_limit_interval.py
sports_odds_api/types/sport.py
sports_odds_api/types/sport_get_response.py
sports_odds_api/types/stat.py
sports_odds_api/types/stat_get_params.py
sports_odds_api/types/stat_get_response.py
sports_odds_api/types/stream_events_params.py
sports_odds_api/types/stream_events_response.py
sports_odds_api/types/team.py
sports_odds_api/types/team_get_params.py
sports_odds_api-1.1.2.dist-info/METADATA
sports_odds_api-1.1.2.dist-info/WHEEL
sports_odds_api-1.1.2.dist-info/licenses/LICENSE
sports_odds_api-1.1.2.dist-info/RECORD
